ggmw/__init__.py
ggmw/core/__init__.py
ggmw/core/async_client.py
ggmw/core/client.py
ggmw/core/exceptions.py
ggmw/core/message.py
ggmw/core/parse_fragment.py
ggmw/core/partial.py
ggmw/core/types.py
ggmw/py.typed
ggmw/tests/__init__.py
ggmw/tests/async_client_test.py
ggmw/tests/client_test.py
ggmw/tests/genai_mock_client.py
ggmw-0.1.3.dist-info/WHEEL
ggmw-0.1.3.dist-info/METADATA
ggmw-0.1.3.dist-info/RECORD
