Metadata-Version: 2.3
Name: ggmw
Version: 0.1.3
Summary: A minimal wrapper for the google gemini (google-genai) API
Author: NovaH00
Author-email: NovaH00 <trantay.nova@gmail.com>
Requires-Dist: anyio>=4.12.0
Requires-Dist: google-genai>=1.56.0
Requires-Dist: partial-json-parser==0.2.1.1.post7
Requires-Dist: pydantic>=2.12.5
Requires-Dist: pytest>=9.0.2
Requires-Dist: pytest-asyncio>=1.3.0
Requires-Dist: pytest-mock>=3.15.1
Requires-Python: >=3.12
